property_finder/__init__.py
property_finder/__main__.py
property_finder/cli.py
property_finder/main.py
property_finder/matrix.py
property_finder-1.0.1.dist-info/entry_points.txt
property_finder-1.0.1.dist-info/METADATA
property_finder-1.0.1.dist-info/WHEEL
property_finder-1.0.1.dist-info/RECORD
