Metadata-Version: 2.1
Name: property-finder
Version: 1.0.1
Summary: Define list of properties for given relation on sets
Author: wnkbll
Author-email: arzhevitin.g@gmail.com
Requires-Python: >=3.12,<4.0
Classifier: Programming Language :: Python :: 3
Classifier: Programming Language :: Python :: 3.12
Requires-Dist: typer (>=0.12.5,<0.13.0)
